streamlit_effects/__init__.py
streamlit_effects/_version.py
streamlit_effects/effects/__init__.py
streamlit_effects/effects/confetti.py
streamlit_effects/effects/fireworks.py
streamlit_effects/effects/hearts.py
streamlit_effects/effects/matrix.py
streamlit_effects/effects/neon_heart.py
streamlit_effects/effects/snow.py
streamlit_effects/frontend/package-lock.json
streamlit_effects/frontend/package.json
streamlit_effects/frontend/rollup.config.js
streamlit_effects/frontend/tsconfig.json
streamlit_effects/frontend/build/StreamlitEffect.d.ts
streamlit_effects/frontend/build/bundle.js
streamlit_effects/frontend/build/bundle.js.map
streamlit_effects/frontend/build/index.d.ts
streamlit_effects/frontend/build/index.html
streamlit_effects/frontend/build/components/ConfettiEffect.d.ts
streamlit_effects/frontend/build/components/FireworksEffect.d.ts
streamlit_effects/frontend/build/components/HeartsEffect.d.ts
streamlit_effects/frontend/build/components/MatrixEffect.d.ts
streamlit_effects/frontend/build/components/SnowEffect.d.ts
streamlit_effects/frontend/build/utils/canvasHelpers.d.ts
streamlit_effects/frontend/build/utils/particleSystem.d.ts
streamlit_effects/frontend/build/utils/types.d.ts
streamlit_effects/frontend/public/index.html
streamlit_effects/frontend/src/StreamlitEffect.tsx
streamlit_effects/frontend/src/index.tsx
streamlit_effects/frontend/src/components/ConfettiEffect.tsx
streamlit_effects/frontend/src/components/FireworksEffect.tsx
streamlit_effects/frontend/src/components/HeartsEffect.tsx
streamlit_effects/frontend/src/components/MatrixEffect.tsx
streamlit_effects/frontend/src/components/SnowEffect.tsx
streamlit_effects/frontend/src/utils/canvasHelpers.ts
streamlit_effects/frontend/src/utils/particleSystem.ts
streamlit_effects/frontend/src/utils/types.ts
streamlit_effects/utils/__init__.py
streamlit_effects/utils/auto_detect.py
streamlit_effects/utils/component_registry.py
streamlit_surfside_labs_ui-0.2.0.dist-info/licenses/LICENSE
streamlit_surfside_labs_ui-0.2.0.dist-info/METADATA
streamlit_surfside_labs_ui-0.2.0.dist-info/WHEEL
streamlit_surfside_labs_ui-0.2.0.dist-info/top_level.txt
streamlit_surfside_labs_ui-0.2.0.dist-info/RECORD
