Metadata-Version: 2.4
Name: streamlit-surfside-labs-ui
Version: 0.2.0
Summary: Animated background effects for Streamlit applications
Home-page: https://github.com/trentmoore/streamlit-effects
Author: Trent Moore
Author-email: Trent Moore <trent@surfsidelabs.com>
License: MIT
Project-URL: Homepage, https://github.com/trentmoore/streamlit-effects
Project-URL: Documentation, https://github.com/trentmoore/streamlit-effects#readme
Project-URL: Repository, https://github.com/trentmoore/streamlit-effects
Project-URL: Issues, https://github.com/trentmoore/streamlit-effects/issues
Keywords: streamlit,components,effects,animations,backgrounds
Classifier: Development Status :: 4 - Beta
Classifier: Intended Audience :: Developers
Classifier: License :: OSI Approved :: MIT License
Classifier: Programming Language :: Python :: 3
Classifier: Programming Language :: Python :: 3.8
Classifier: Programming Language :: Python :: 3.9
Classifier: Programming Language :: Python :: 3.10
Classifier: Programming Language :: Python :: 3.11
Classifier: Programming Language :: Python :: 3.12
Requires-Python: >=3.8
License-File: LICENSE
Requires-Dist: streamlit>=1.20.0
Provides-Extra: dev
Requires-Dist: pytest>=7.0.0; extra == "dev"
Requires-Dist: black>=22.0.0; extra == "dev"
Requires-Dist: mypy>=0.990; extra == "dev"
Dynamic: author
Dynamic: home-page
Dynamic: license-file
Dynamic: requires-python
